simple_tools/__init__.py
simple_tools/debugger.py
simple_tools/type_checker.py
simple_tools_jacobitosuperstar-0.0.0.dist-info/LICENSE
simple_tools_jacobitosuperstar-0.0.0.dist-info/METADATA
simple_tools_jacobitosuperstar-0.0.0.dist-info/WHEEL
simple_tools_jacobitosuperstar-0.0.0.dist-info/top_level.txt
simple_tools_jacobitosuperstar-0.0.0.dist-info/RECORD
