Metadata-Version: 2.1
Name: simple-tools-jacobitosuperstar
Version: 0.0.0
Summary: simple tools to ease the use of more complex python functions
Home-page: https://github.com/jacobitosuperstar/simple_tools
Author: Jacobo Mateo Bedoya Oquendo
License: MIT
Project-URL: Source, https://github.com/jacobitosuperstar/simple_tools
Project-URL: Tracker, https://github.com/jacobitosuperstar/simple_tools/issues
Platform: unix
Platform: linux
Platform: osx
Platform: cygwin
Platform: win32
Classifier: Programming Language :: Python :: 3
Classifier: Programming Language :: Python :: 3 :: Only
Classifier: Programming Language :: Python :: 3.8
Classifier: Programming Language :: Python :: 3.9
Classifier: Programming Language :: Python :: 3.10
Classifier: Operating System :: OS Independent
Classifier: Intended Audience :: Developers
Classifier: Topic :: Software Development :: Libraries :: Python Modules
Requires-Python: >=3.8
License-File: LICENSE
Provides-Extra: testing
Requires-Dist: flake8 (>=3.9) ; extra == 'testing'
